ghs_parser/__init__.py
ghs_parser/func.py
ghs_parser/icons/GHS01-acid.png
ghs_parser/icons/GHS02-flamme.png
ghs_parser/icons/GHS03-oxidizing.png
ghs_parser/icons/GHS04-glass.png
ghs_parser/icons/GHS05-corrosive.png
ghs_parser/icons/GHS06-toxic.png
ghs_parser/icons/GHS07-health.png
ghs_parser/icons/GHS08-silhouette.png
ghs_parser/icons/GHS09-env.png
ghs_parser-0.1.3.dist-info/METADATA
ghs_parser-0.1.3.dist-info/WHEEL
ghs_parser-0.1.3.dist-info/top_level.txt
ghs_parser-0.1.3.dist-info/RECORD
