Metadata-Version: 2.4
Name: ghs-parser
Version: 0.1.3
Summary: Parser for detecting GHS icons in PDFs
Author-email: Adilkhan <adilhanzai@gmail.com>
Classifier: Programming Language :: Python :: 3
Classifier: License :: OSI Approved :: MIT License
Classifier: Operating System :: OS Independent
Requires-Python: >=3.9
Requires-Dist: numpy==2.2.6
Requires-Dist: opencv-python==4.12.0.88
Requires-Dist: PyMuPDF==1.26.6
